mltk/__init__.py
mltk/datatools.py
mltk/deploy.py
mltk/etl.py
mltk/explain.py
mltk/explore.py
mltk/image.py
mltk/matrics.py
mltk/model.py
mltk/modelchest.py
mltk/project.py
mltk/server.py
mltk/server_api_sdk.py
mltk/string.py
pymltoolkit-0.1.11.dist-info/LICENSE.txt
pymltoolkit-0.1.11.dist-info/METADATA
pymltoolkit-0.1.11.dist-info/WHEEL
pymltoolkit-0.1.11.dist-info/top_level.txt
pymltoolkit-0.1.11.dist-info/RECORD
